<?xml version="1.0" encoding="utf-8"?>
<!-- Ecologist_Agenda -->
<!-- Author: blkbutterfly74 -->
<!-- DateCreated: 5/23/2021 8:24:12 AM -->
<GameInfo>
	<Types>
		<Row Type="TRAIT_AGENDA_PREFER_PRESERVATION" Kind="KIND_TRAIT"/>
	</Types>

	<Traits>
		<Row TraitType="TRAIT_AGENDA_PREFER_PRESERVATION"/>
	</Traits>

	<Agendas>
		<Row AgendaType="AGENDA_ECOLOGIST" Name="LOC_AGENDA_ECOLOGIST_NAME" Description="LOC_AGENDA_ECOLOGIST_DESCRIPTION"/>
	</Agendas>

	<RandomAgendas>
		<Row AgendaType="AGENDA_ECOLOGIST"/>

		<!-- remove other random agendas -->
		<Delete AgendaType="AGENDA_AIRPOWER"/>
		<Delete AgendaType="AGENDA_CITY_STATE_ALLY"/>
		<Delete AgendaType="AGENDA_CITY_STATE_PROTECTOR"/>
		<Delete AgendaType="AGENDA_CIVILIZED"/>
		<Delete AgendaType="AGENDA_CULTURED"/>
		<Delete AgendaType="AGENDA_DARWINIST"/>
		<Delete AgendaType="AGENDA_DEVOUT"/>
		<Delete AgendaType="AGENDA_EXPLOITATIVE"/>
		<Delete AgendaType="AGENDA_EXPLORER"/>
		<Delete AgendaType="AGENDA_FUN_LOVING"/>
		<Delete AgendaType="AGENDA_GREAT_PERSON_ADVOCATE"/>
		<Delete AgendaType="AGENDA_IDEOLOGUE"/>
		<Delete AgendaType="AGENDA_INDUSTRIALIST"/>
		<Delete AgendaType="AGENDA_MONEY_GRUBBER"/>
		<Delete AgendaType="AGENDA_NUKE_LOVER"/>
		<Delete AgendaType="AGENDA_PARANOID"/>
		<Delete AgendaType="AGENDA_POPULOUS"/>
		<Delete AgendaType="AGENDA_STANDING_ARMY"/>
		<Delete AgendaType="AGENDA_TECHNOPHILE"/>
		<Delete AgendaType="AGENDA_WONDER_ADVOCATE"/>
	</RandomAgendas>

	<Types>
		<!-- - Agendas -->
		<Delete Type="TRAIT_AGENDA_ALLY_OF_ENKIDU"/>
		<Delete Type="TRAIT_AGENDA_AYYUBID_DYNASTY"/>
		<Delete Type="TRAIT_AGENDA_BACKSTAB_AVERSE"/>
		<Delete Type="TRAIT_AGENDA_BARBARIAN_LOVER"/>
		<Delete Type="TRAIT_AGENDA_BUSHIDO"/>
		<Delete Type="TRAIT_AGENDA_DELIAN_LEAGUE"/>
		<Delete Type="TRAIT_AGENDA_ENTHUSIASTIC_DISCIPLE"/>
		<Delete Type="TRAIT_AGENDA_GREAT_PERSON_OBSESSED"/>
		<Delete Type="TRAIT_AGENDA_IRON_CROWN"/>
		<Delete Type="TRAIT_AGENDA_LAST_VIKING_KING"/>
		<Delete Type="TRAIT_AGENDA_OPTIMUS_PRINCEPS"/>
		<Delete Type="TRAIT_AGENDA_PEACEKEEPER"/>
		<Delete Type="TRAIT_AGENDA_QUEEN_OF_NILE"/>
		<Delete Type="TRAIT_AGENDA_WESTERNIZER"/>
		<Delete Type="TRAIT_AGENDA_WITH_SHIELD"/>
		<Delete Type="TRAIT_AGENDA_WONDER_OBSESSED"/>
		<Delete Type="TRAIT_AGENDA_WONDER_ADVOCATE"/>
		<Delete Type="TRAIT_AGENDA_PREFER_CLEAR_BANDIT_CAMPS"/>
		<Delete Type="TRAIT_AGENDA_ENJOYS_WAR"/>
		<Delete Type="TRAIT_AGENDA_IGNORE_WARMONGERING"/>
		<Delete Type="TRAIT_AGENDA_PREFER_NUKES"/>
		<Delete Type="TRAIT_AGENDA_PARANOID"/>
		<Delete Type="TRAIT_AGENDA_PREFER_POPULATION"/>
		<Delete Type="TRAIT_AGENDA_PREFER_CULTURE"/>
		<Delete Type="TRAIT_AGENDA_PREFER_HAPPINESS"/>
		<Delete Type="TRAIT_AGENDA_PREFER_INCOME"/>
		<Delete Type="TRAIT_AGENDA_PREFER_SCIENCE"/>
		<Delete Type="TRAIT_AGENDA_PREFER_STANDING_ARMY"/>
		<Delete Type="TRAIT_AGENDA_PREFER_AIRPOWER"/>
		<Delete Type="TRAIT_AGENDA_PREFER_CITY_STATE_PROTECTOR"/>
		<Delete Type="TRAIT_AGENDA_PREFER_EXPLOITATION"/>
		<Delete Type="TRAIT_AGENDA_PREFER_SAME_GOVERNMENT"/>
		<Delete Type="TRAIT_AGENDA_EXPLORATION_OBSESSED"/>
		<Delete Type="TRAIT_AGENDA_GREAT_PERSON_ADVOCATE"/>
		<Delete Type="TRAIT_AGENDA_END_TO_SUFFERING"/>
		<Delete Type="TRAIT_AGENDA_ARCHIPELAGIC_STATE"/>
		<Delete Type="TRAIT_AGENDA_SHORT_LIFE_GLORY"/>
		<Delete Type="TRAIT_AGENDA_BACKSTABBER"/>
		<Delete Type="TRAIT_AGENDA_PREFER_INDUSTRY"/>
		<Delete Type="TRAIT_AGENDA_CITY_STATE_ALLY"/>
		<Delete Type="TRAIT_AGENDA_PREFER_FAITH"/>
		<Delete Type="TRAIT_AGENDA_TRIEU_DEFENDER"/>
		<Delete Type="TRAIT_AGENDA_KUBLAI_PAX"/>
	</Types>

	<AgendaTraits>
		<Row AgendaType="AGENDA_ECOLOGIST" TraitType="TRAIT_AGENDA_PREFER_PRESERVATION"/>
	</AgendaTraits>

	<AiLists>
		<Row ListType="PreservationBuildings" AgendaType="TRAIT_AGENDA_PREFER_PRESERVATION" System="Buildings"/>
		<Row ListType="PreservationDistricts" AgendaType="TRAIT_AGENDA_PREFER_PRESERVATION" System="Districts"/>
	</AiLists>

	<AiFavoredItems>
		<Row ListType="PreservationBuildings" Item="BUILDING_SANCTUARY" Favored="1"/>
		<Row ListType="PreservationBuildings" Item="BUILDING_GROVE" Favored="1"/>
		<Row ListType="PreservationDistricts" Item="DISTRICT_PRESERVE" Favored="1"/>
	</AiFavoredItems>

	<AiListTypes>
		<Row ListType="PreservationBuildings"/>
		<Row ListType="PreservationDistricts"/>
	</AiListTypes>

	<AgendaPreferredLeaders>
		<!-- Pedro should also be an environmentalist -->
		<Row AgendaType="AGENDA_ENVIRONMENTALIST" LeaderType="LEADER_PEDRO" PercentageChance="50"/>
		<Row AgendaType="AGENDA_ECOLOGIST" LeaderType="LEADER_PEDRO" PercentageChance="50"/>

		<!-- Bull Moose Teddy is bumped -->
		<Update>
			<Where>
				<AgendaType>AGENDA_ENVIRONMENTALIST</AgendaType>
				<LeaderType>LEADER_T_ROOSEVELT</LeaderType>
			</Where>
			<Set>
				<PercentageChance>66</PercentageChance>
			</Set>
		</Update>
		<Row AgendaType="AGENDA_ECOLOGIST" LeaderType="LEADER_T_ROOSEVELT" PercentageChance="33"/>

		<Row AgendaType="AGENDA_ECOLOGIST" LeaderType="LEADER_CATHERINE_DE_MEDICI" PercentageChance="85"/>
		<Row AgendaType="AGENDA_ECOLOGIST" LeaderType="LEADER_PHILIP_II" PercentageChance="90"/>

		<Row AgendaType="AGENDA_ECOLOGIST" LeaderType="LEADER_CATHERINE_DE_MEDICI_ALT" PercentageChance="90"/>
		<Row AgendaType="AGENDA_ECOLOGIST" LeaderType="LEADER_MONTEZUMA" PercentageChance="90"/>
		<Row AgendaType="AGENDA_ECOLOGIST" LeaderType="LEADER_T_ROOSEVELT_ROUGHRIDER" PercentageChance="90"/>
		<Row AgendaType="AGENDA_ECOLOGIST" LeaderType="LEADER_VICTORIA" PercentageChance="90"/>
		<Row AgendaType="AGENDA_ECOLOGIST" LeaderType="LEADER_LADY_SIX_SKY" PercentageChance="90"/>
		<Row AgendaType="AGENDA_ECOLOGIST" LeaderType="LEADER_SIMON_BOLIVAR" PercentageChance="90"/>
		<Row AgendaType="AGENDA_ECOLOGIST" LeaderType="LEADER_JOAO_III" PercentageChance="90"/>
	</AgendaPreferredLeaders>

	<!-- AI strategy for Ecologist agenda -->
	<Strategies>
		<Delete StrategyType="STRATEGY_WONDER_OBSESSED" />

		<Row StrategyType="STRATEGY_ECOLOGIST" NumConditionsNeeded="1"/>
	</Strategies>

	<StrategyConditions>
		<Row StrategyType="STRATEGY_ECOLOGIST" ConditionFunction="Has Agenda" StringValue="AGENDA_ECOLOGIST"/>
	</StrategyConditions>

	<Strategy_Priorities>
		<Row StrategyType="STRATEGY_ECOLOGIST" ListType="PreservationBuildings"/>
		<Row StrategyType="STRATEGY_ECOLOGIST" ListType="PreservationDistricts"/>
	</Strategy_Priorities>
</GameInfo>
